odoo/addons/sale_invoicing_date_selection/README.rst
odoo/addons/sale_invoicing_date_selection/__init__.py
odoo/addons/sale_invoicing_date_selection/__manifest__.py
odoo/addons/sale_invoicing_date_selection/i18n/es.po
odoo/addons/sale_invoicing_date_selection/i18n/it.po
odoo/addons/sale_invoicing_date_selection/i18n/sale_invoicing_date_selection.pot
odoo/addons/sale_invoicing_date_selection/models/__init__.py
odoo/addons/sale_invoicing_date_selection/models/sale_order.py
odoo/addons/sale_invoicing_date_selection/readme/CONTRIBUTORS.md
odoo/addons/sale_invoicing_date_selection/readme/DESCRIPTION.md
odoo/addons/sale_invoicing_date_selection/readme/USAGE.md
odoo/addons/sale_invoicing_date_selection/static/description/icon.png
odoo/addons/sale_invoicing_date_selection/static/description/index.html
odoo/addons/sale_invoicing_date_selection/tests/__init__.py
odoo/addons/sale_invoicing_date_selection/tests/test_sale_invoicing_date_selection.py
odoo/addons/sale_invoicing_date_selection/wizard/__init__.py
odoo/addons/sale_invoicing_date_selection/wizard/sale_advance_payment_inv.py
odoo/addons/sale_invoicing_date_selection/wizard/sale_make_invoice_advance_views.xml
odoo_addon_sale_invoicing_date_selection-17.0.1.0.1.dist-info/METADATA
odoo_addon_sale_invoicing_date_selection-17.0.1.0.1.dist-info/WHEEL
odoo_addon_sale_invoicing_date_selection-17.0.1.0.1.dist-info/top_level.txt
odoo_addon_sale_invoicing_date_selection-17.0.1.0.1.dist-info/RECORD
